nsj_rest_test_util/__init__.py
nsj_rest_test_util/dao/__init__.py
nsj_rest_test_util/dao/db_pool_config.py
nsj_rest_test_util/dao/settings.py
nsj_rest_test_util/dao/entity/__init__.py
nsj_rest_test_util/dao/entity/enum_custom.py
nsj_rest_test_util/dao/exception/__init__.py
nsj_rest_test_util/dao/exception/exception.py
nsj_rest_test_util/dao/exception/repetir_exception.py
nsj_rest_test_util/dao/factory/__init__.py
nsj_rest_test_util/dao/factory/util_factory.py
nsj_rest_test_util/dao/repository/__init__.py
nsj_rest_test_util/dao/repository/abstract_repository.py
nsj_rest_test_util/dao/repository/testes_repository.py
nsj_rest_test_util/util/__init__.py
nsj_rest_test_util/util/assert_util.py
nsj_rest_test_util/util/backup_util.py
nsj_rest_test_util/util/cursor_util.py
nsj_rest_test_util/util/dump_util.py
nsj_rest_test_util/util/enum_http_method.py
nsj_rest_test_util/util/enum_param_mode.py
nsj_rest_test_util/util/globals_util.py
nsj_rest_test_util/util/json_util.py
nsj_rest_test_util/util/requests_util.py
nsj_rest_test_util/util/tcase_tools.py
nsj_rest_test_util/util/tcase_util.py
nsj_rest_test_util/util/validate_util.py
nsj_rest_test_util-0.1.14.dist-info/METADATA
nsj_rest_test_util-0.1.14.dist-info/WHEEL
nsj_rest_test_util-0.1.14.dist-info/top_level.txt
nsj_rest_test_util-0.1.14.dist-info/RECORD
