Metadata-Version: 2.4
Name: nsj-rest-test-util
Version: 0.1.14
Summary: Utilitários para testes de aplicações rests.
Home-page: https://github.com/Nasajon/nsj-rest-test-util
Author: Nasajon Sistemas
Author-email: contact.dev@nasajon.com.br
Project-URL: Source, https://github.com/Nasajon/nsj-rest-test-util
Classifier: Development Status :: 3 - Alpha
Classifier: Intended Audience :: Developers
Classifier: Topic :: Software Development :: Build Tools
Classifier: Programming Language :: Python :: 3
Requires-Python: >=3.4
Requires-Dist: asn1crypto>=1.5.1
Requires-Dist: attrs>=22.1.0
Requires-Dist: Authlib>=1.0.0
Requires-Dist: certifi>=2022.9.24
Requires-Dist: cffi>=1.15.1
Requires-Dist: charset-normalizer>=2.0.12
Requires-Dist: click>=8.1.3
Requires-Dist: cryptography>=38.0.1
Requires-Dist: Flask>=2.0.3
Requires-Dist: greenlet>=1.1.3
Requires-Dist: idna>=3.4
Requires-Dist: iniconfig>=1.1.1
Requires-Dist: itsdangerous>=2.1.2
Requires-Dist: Jinja2>=3.1.2
Requires-Dist: jsonpickle>=2.2.0
Requires-Dist: MarkupSafe>=2.1.1
Requires-Dist: nsj-gcf-utils>=1.0.9
Requires-Dist: packaging>=21.3
Requires-Dist: pendulum>=2.1.2
Requires-Dist: pg8000>=1.24.1
Requires-Dist: pluggy>=1.0.0
Requires-Dist: ptvsd>=4.3.2
Requires-Dist: py>=1.11.0
Requires-Dist: pycparser>=2.21
Requires-Dist: pydantic>=1.9.0
Requires-Dist: pyparsing>=3.0.9
Requires-Dist: pytest>=7.1.3
Requires-Dist: python-dateutil>=2.8.2
Requires-Dist: pytzdata>=2020.1
Requires-Dist: requests>=2.26.0
Requires-Dist: scramp>=1.4.1
Requires-Dist: six>=1.16.0
Requires-Dist: SQLAlchemy>=1.4.32
Requires-Dist: sqlparams>=3.0.0
Requires-Dist: tomli>=2.0.1
Requires-Dist: typing_extensions>=4.3.0
Requires-Dist: urllib3>=1.26.12
Requires-Dist: Werkzeug>=2.2.2
